redisAioSpider/__init__.py
redisAioSpider/main.py
redisAioSpider/baseSpider/__init__.py
redisAioSpider/baseSpider/base.py
redisAioSpider/baseSpider/normalSpiderBase.py
redisAioSpider/baseSpider/redisSpiderBase.py
redisAioSpider/components/__init__.py
redisAioSpider/components/saveToMysql.py
redisAioSpider/config/__init__.py
redisAioSpider/config/redis_config.py
redisAioSpider/config/sql_config.py
redisAioSpider/logger/__init__.py
redisAioSpider/logger/logger.py
redisAioSpider/spider/__init__.py
redisAioSpider/spider/demo.py
redisAioSpider/utils/__init__.py
redisAioSpider/utils/aioMysqlConnet.py
redisAioSpider/utils/aioRedisConncet.py
redisAioSpider/utils/startSpider.py
redisAioSpider/utils/tools.py
redisAioSpider-1.1.2.dist-info/METADATA
redisAioSpider-1.1.2.dist-info/WHEEL
redisAioSpider-1.1.2.dist-info/top_level.txt
redisAioSpider-1.1.2.dist-info/RECORD
